{
  "HALProvider": {
    "Other Devices": {
      "SPARK MAX [1]": {
        "header": {
          "open": true
        }
      }
    }
  },
  "NTProvider": {
    "types": {
      "/FMSInfo": "FMSInfo",
      "/SmartDashboard/Field": "Field2d"
    },
    "windows": {
      "/SmartDashboard/Field": {
        "Robot": {
          "arrowColor": [
            0.06547617167234421,
            0.7857142686843872,
            0.7085458636283875,
            255.0
          ],
          "color": [
            1.0,
            1.0,
            1.0,
            255.0
          ]
        },
        "window": {
          "visible": true
        }
      }
    }
  },
  "NetworkTables": {
    "transitory": {
      "LiveWindow": {
        "open": true
      },
      "SmartDashboard": {
        "open": true
      },
      "photonvision": {
        "open": true
      }
    }
  },
  "NetworkTables Info": {
    "Connections": {
      "open": true
    },
    "Server": {
      "Publishers": {
        "open": true
      },
      "open": true
    }
  },
  "Plot": {
    "Plot <0>": {
      "window": {
        "visible": false
      }
    }
  }
}
